monzopy/__init__.py
monzopy/monzopy.py
monzopy/py.typed
monzopy-1.5.1.dist-info/licenses/LICENSE
monzopy-1.5.1.dist-info/METADATA
monzopy-1.5.1.dist-info/WHEEL
monzopy-1.5.1.dist-info/top_level.txt
monzopy-1.5.1.dist-info/RECORD
