Metadata-Version: 2.4
Name: monzopy
Version: 1.5.1
Summary: A simple async python wrapper for the Monzo API, used primarily by the Monzo Home Assistant integration.
Author-email: Jake Martin <jake_martin_@outlook.com>
Project-URL: Homepage, https://github.com/JakeMartin-ICL/monzopy
Project-URL: Bug Tracker, https://github.com/JakeMartin-ICL/monzopy/issues
Classifier: Programming Language :: Python :: 3
Classifier: License :: OSI Approved :: GNU General Public License v3 (GPLv3)
Classifier: Operating System :: OS Independent
Requires-Python: >=3.7
License-File: LICENSE
Requires-Dist: aiohttp>=3.0.0
Dynamic: license-file
